{
    "shared_resources": {
        "resource_group": {
            "name": "bgc-shared-rg",
            "location": "eastus2"
        },
        "storage_account": {
            "name": "bgcsharedst",
            "terraform_container_name_dev": "tfstate-dev",
            "terraform_container_name_prod": "tfstate-prod"
        },
        "container_registry": {
            "name": "bgcsharedcr",
            "sku": "Basic"
        },
        "analytics_workspace": {
            "name": "bgc-shared-log",
            "retention_in_days": 30,
            "sku": "PerGB2018"
        },
        "application_insights": {
            "apim": {
                "name": "bgc-shared-apim-appi",
                "insights_name": "apim-insights"
            },
            "search_api_health_test": {
                "name": "bgc-search-api-health-test"
            }
        },
        "apim": {
            "name": "bgc-shared-apim",
            "sku": "Consumption_0"
        }
    }
}